interviewing/__init__.py
interviewing/questions/__init__.py
interviewing/questions/buy_and_sell_a_stock_once.py
interviewing-0.0.5.dist-info/LICENSE
interviewing-0.0.5.dist-info/WHEEL
interviewing-0.0.5.dist-info/METADATA
interviewing-0.0.5.dist-info/RECORD
