Metadata-Version: 2.1
Name: interviewing
Version: 0.0.5
Summary: A sassy package for shaming unimaginative interviewers.
Author-email: Alec Johnson <alec@ayyjohn.com>
Requires-Python: >=3.8
Classifier: License :: OSI Approved :: MIT License
Project-URL: Home, https://github.com/ayyjohn/interviewing
Project-URL: Source, https://github.com/ayyjohn/interviewing
Project-URL: Tracker, https://github.com/ayyjohn/interviewing/issues
